<?xml version="1.0" encoding="UTF-8"?><TED_EXPORT xmlns:xlink="http://www.w3.org/1999/xlink" xmlns:xsi="http://www.w3.org/2001/XMLSchema-instance" xmlns="http://publications.europa.eu/resource/schema/ted/R2.0.9/publication" xmlns:n2016="http://publications.europa.eu/resource/schema/ted/2016/nuts" xsi:schemaLocation="http://publications.europa.eu/resource/schema/ted/R2.0.9/publication TED_EXPORT.xsd" VERSION="R2.0.9.S03.E01" DOC_ID="479633-2020" EDITION="2020198"><TECHNICAL_SECTION><RECEPTION_ID>20-494848-001</RECEPTION_ID><DELETION_DATE>20210115</DELETION_DATE><FORM_LG_LIST>PL </FORM_LG_LIST><COMMENTS>From Convertor</COMMENTS></TECHNICAL_SECTION><LINKS_SECTION><XML_SCHEMA_DEFINITION_LINK xlink:type="simple" xlink:href="http://ted.europa.eu" xlink:title="TED WEBSITE"/><OFFICIAL_FORMS_LINK xlink:type="simple" xlink:href="http://ted.europa.eu"/><FORMS_LABELS_LINK xlink:type="simple" xlink:href="http://ted.europa.eu"/><ORIGINAL_CPV_LINK xlink:type="simple" xlink:href="http://ted.europa.eu"/><ORIGINAL_NUTS_LINK xlink:type="simple" xlink:href="http://ted.europa.eu"/></LINKS_SECTION><CODED_DATA_SECTION><REF_OJS><COLL_OJ>S</COLL_OJ><NO_OJ>198</NO_OJ><DATE_PUB>20201012</DATE_PUB></REF_OJS><NOTICE_DATA><NO_DOC_OJS>2020/S 198-479633</NO_DOC_OJS><URI_LIST><URI_DOC LG="PL">http://ted.europa.eu/udl?uri=TED:NOTICE:479633-2020:TEXT:PL:HTML</URI_DOC></URI_LIST><LG_ORIG>PL</LG_ORIG><ISO_COUNTRY VALUE="PL"/><IA_URL_GENERAL>http://www.skw.gov.pl/</IA_URL_GENERAL><ORIGINAL_CPV CODE="35811300">Military uniforms</ORIGINAL_CPV><ORIGINAL_CPV CODE="18443310">Berets</ORIGINAL_CPV><ORIGINAL_CPV CODE="18440000">Hats and headgear</ORIGINAL_CPV><ORIGINAL_CPV CODE="18443320">Field caps</ORIGINAL_CPV><ORIGINAL_CPV CODE="18832000">Special footwear</ORIGINAL_CPV><ORIGINAL_CPV CODE="35113470">Protective shirts or pants</ORIGINAL_CPV><ORIGINAL_CPV CODE="18424000">Gloves</ORIGINAL_CPV><ORIGINAL_CPV CODE="37414100">Sleeping pads</ORIGINAL_CPV><ORIGINAL_CPV CODE="18323000">Suspenders</ORIGINAL_CPV><ORIGINAL_CPV CODE="18425000">Belts</ORIGINAL_CPV><ORIGINAL_CPV CODE="18317000">Socks</ORIGINAL_CPV><ORIGINAL_CPV CODE="18310000">Underwear</ORIGINAL_CPV><n2016:PERFORMANCE_NUTS CODE="PL">POLSKA</n2016:PERFORMANCE_NUTS><n2016:CA_CE_NUTS CODE="PL911">Miasto Warszawa</n2016:CA_CE_NUTS><n2016:TENDERER_NUTS CODE="PL">POLSKA</n2016:TENDERER_NUTS><VALUES><VALUE TYPE="PROCUREMENT_TOTAL" CURRENCY="PLN">2036504.06</VALUE></VALUES><REF_NOTICE><NO_DOC_OJS>2020/S 125-305874</NO_DOC_OJS></REF_NOTICE></NOTICE_DATA><CODIF_DATA><DS_DATE_DISPATCH>20201007</DS_DATE_DISPATCH><AA_AUTHORITY_TYPE CODE="1">Ministry or any other national or federal authority</AA_AUTHORITY_TYPE><TD_DOCUMENT_TYPE CODE="7">Contract award notice</TD_DOCUMENT_TYPE><NC_CONTRACT_NATURE CODE="2">Supplies</NC_CONTRACT_NATURE><PR_PROC CODE="1">Open procedure</PR_PROC><RP_REGULATION CODE="4">European Union</RP_REGULATION><TY_TYPE_BID CODE="9">Not applicable</TY_TYPE_BID><AC_AWARD_CRIT CODE="1">Lowest price</AC_AWARD_CRIT><MA_MAIN_ACTIVITIES CODE="D">Defence</MA_MAIN_ACTIVITIES><HEADING>01B03</HEADING><INITIATOR>01</INITIATOR></CODIF_DATA></CODED_DATA_SECTION><TRANSLATION_SECTION><ML_TITLES><ML_TI_DOC LG="BG"><TI_CY>Полша</TI_CY><TI_TOWN>Варшава</TI_TOWN><TI_TEXT><P>Военни униформи</P></TI_TEXT></ML_TI_DOC><ML_TI_DOC LG="CS"><TI_CY>Polsko</TI_CY><TI_TOWN>Varšava</TI_TOWN><TI_TEXT><P>Vojenské uniformy</P></TI_TEXT></ML_TI_DOC><ML_TI_DOC LG="DA"><TI_CY>Polen</TI_CY><TI_TOWN>Warszawa</TI_TOWN><TI_TEXT><P>Uniformer til militæret</P></TI_TEXT></ML_TI_DOC><ML_TI_DOC LG="DE"><TI_CY>Polen</TI_CY><TI_TOWN>Warschau</TI_TOWN><TI_TEXT><P>Militäruniformen</P></TI_TEXT></ML_TI_DOC><ML_TI_DOC LG="EL"><TI_CY>Πολωνία</TI_CY><TI_TOWN>Βαρσοβία</TI_TOWN><TI_TEXT><P>Στρατιωτικές στολές</P></TI_TEXT></ML_TI_DOC><ML_TI_DOC LG="EN"><TI_CY>Poland</TI_CY><TI_TOWN>Warsaw</TI_TOWN><TI_TEXT><P>Military uniforms</P></TI_TEXT></ML_TI_DOC><ML_TI_DOC LG="ES"><TI_CY>Polonia</TI_CY><TI_TOWN>Varsovia</TI_TOWN><TI_TEXT><P>Uniformes militares</P></TI_TEXT></ML_TI_DOC><ML_TI_DOC LG="ET"><TI_CY>Poola</TI_CY><TI_TOWN>Varssavi</TI_TOWN><TI_TEXT><P>Sõjaväevorm</P></TI_TEXT></ML_TI_DOC><ML_TI_DOC LG="FI"><TI_CY>Puola</TI_CY><TI_TOWN>Varsova</TI_TOWN><TI_TEXT><P>Sotilasvirkapuvut</P></TI_TEXT></ML_TI_DOC><ML_TI_DOC LG="FR"><TI_CY>Pologne</TI_CY><TI_TOWN>Varsovie</TI_TOWN><TI_TEXT><P>Uniformes militaires</P></TI_TEXT></ML_TI_DOC><ML_TI_DOC LG="GA"><TI_CY>Pholainn, an</TI_CY><TI_TOWN>Vársá</TI_TOWN><TI_TEXT><P>Military uniforms</P></TI_TEXT></ML_TI_DOC><ML_TI_DOC LG="HR"><TI_CY>Poljska</TI_CY><TI_TOWN>Varšava</TI_TOWN><TI_TEXT><P>Vojne uniforme</P></TI_TEXT></ML_TI_DOC><ML_TI_DOC LG="HU"><TI_CY>Lengyelország</TI_CY><TI_TOWN>Varsó</TI_TOWN><TI_TEXT><P>Katonai egyenruha</P></TI_TEXT></ML_TI_DOC><ML_TI_DOC LG="IT"><TI_CY>Polonia</TI_CY><TI_TOWN>Varsavia</TI_TOWN><TI_TEXT><P>Uniformi per militari</P></TI_TEXT></ML_TI_DOC><ML_TI_DOC LG="LT"><TI_CY>Lenkija</TI_CY><TI_TOWN>Varšuva</TI_TOWN><TI_TEXT><P>Kariškių uniformos</P></TI_TEXT></ML_TI_DOC><ML_TI_DOC LG="LV"><TI_CY>Polija</TI_CY><TI_TOWN>Varšava</TI_TOWN><TI_TEXT><P>Militārie formas tērpi</P></TI_TEXT></ML_TI_DOC><ML_TI_DOC LG="MT"><TI_CY>il-Polonja</TI_CY><TI_TOWN>Varsavja</TI_TOWN><TI_TEXT><P>Uniformijiet tal-militar</P></TI_TEXT></ML_TI_DOC><ML_TI_DOC LG="NL"><TI_CY>Polen</TI_CY><TI_TOWN>Warschau</TI_TOWN><TI_TEXT><P>Militaire uniformen</P></TI_TEXT></ML_TI_DOC><ML_TI_DOC LG="PL"><TI_CY>Polska</TI_CY><TI_TOWN>Warszawa</TI_TOWN><TI_TEXT><P>Mundury wojskowe</P></TI_TEXT></ML_TI_DOC><ML_TI_DOC LG="PT"><TI_CY>Polónia</TI_CY><TI_TOWN>Varsóvia</TI_TOWN><TI_TEXT><P>Uniformes militares</P></TI_TEXT></ML_TI_DOC><ML_TI_DOC LG="RO"><TI_CY>Polonia</TI_CY><TI_TOWN>Varşovia</TI_TOWN><TI_TEXT><P>Uniforme militare</P></TI_TEXT></ML_TI_DOC><ML_TI_DOC LG="SK"><TI_CY>Poľsko</TI_CY><TI_TOWN>Varšava</TI_TOWN><TI_TEXT><P>Vojenské uniformy</P></TI_TEXT></ML_TI_DOC><ML_TI_DOC LG="SL"><TI_CY>Poljska</TI_CY><TI_TOWN>Varšava</TI_TOWN><TI_TEXT><P>Vojaške uniforme</P></TI_TEXT></ML_TI_DOC><ML_TI_DOC LG="SV"><TI_CY>Polen</TI_CY><TI_TOWN>Warszawa</TI_TOWN><TI_TEXT><P>Militära uniformer</P></TI_TEXT></ML_TI_DOC></ML_TITLES><ML_AA_NAMES><AA_NAME LG="PL">Służba Kontrwywiadu Wojskowego</AA_NAME></ML_AA_NAMES></TRANSLATION_SECTION><FORM_SECTION><F03_2014 CATEGORY="ORIGINAL" FORM="F03" LG="PL"><LEGAL_BASIS VALUE="32014L0024"/><CONTRACTING_BODY><ADDRESS_CONTRACTING_BODY><OFFICIALNAME>Służba Kontrwywiadu Wojskowego</OFFICIALNAME><ADDRESS>ul. W. Oczki 1</ADDRESS><TOWN>Warszawa</TOWN><POSTAL_CODE>02-007</POSTAL_CODE><COUNTRY VALUE="PL"/><CONTACT_POINT>Sylwia Sumka</CONTACT_POINT><PHONE>+48 261841209/ +48 261841119</PHONE><E_MAIL>zamowienia@skw.gov.pl</E_MAIL><n2016:NUTS CODE="PL911"/><URL_GENERAL>http://www.skw.gov.pl/</URL_GENERAL></ADDRESS_CONTRACTING_BODY><CA_TYPE VALUE="MINISTRY"/><CA_ACTIVITY VALUE="DEFENCE"/></CONTRACTING_BODY><OBJECT_CONTRACT><TITLE><P>Dostawa umundurowania</P></TITLE><REFERENCE_NUMBER>ZP-16-SKW-2020</REFERENCE_NUMBER><CPV_MAIN><CPV_CODE CODE="35811300"/></CPV_MAIN><TYPE_CONTRACT CTYPE="SUPPLIES"/><SHORT_DESCR><P>Przedmiotem zamówienia jest dostawa umundurowania, zgodnie ze wszystkimi wymaganiami Zamawiającego. Przedmiot zamówienia został podzielony na 18 części:</P><P>— część nr 1: beret zielony – 300 szt.,</P><P>— część nr 2: furażerka polowa Sił Powietrznych – 100 szt.,</P><P>— część nr 3: czapka zimowa – 500 szt.,</P><P>— część nr 4: trzewiki w ilości 550 par.,</P><P>— część nr 5: trzewiki zimowe – 550 par.,</P><P>— część nr 6: ubranie ochronne – 500 kpl.,</P><P>— część nr 7: mundur polowy – 600 kpl.,</P><P>— część nr 8: mundur polowy letni – 600 kpl.,</P><P>— część nr 9: koszulo bluza polowa – 400 szt.,</P><P>— część nr 10: rękawice zimowe pięciopalcowe – 400 par.,</P><P>— część nr 11: karimata – 200 szt.,</P><P>— część nr 12: szelki do przenoszenia oporządzenia – 200 szt.,</P><P>— część nr 13: pas żołnierski – 200 szt.,</P><P>— część nr 14: skarpety zimowe – 1 500 par.,</P><P>— część nr 15: skarpety letnie – 1 000 par.,</P><P>— część nr 16: bielizna zimowa – 1 000 kpl.,</P><P>— część nr 17: bielizna letnia – 1 000 kpl.,</P><P>— część nr 18: bluza ocieplająca – 250 szt.</P></SHORT_DESCR><VAL_TOTAL CURRENCY="PLN">2036504.06</VAL_TOTAL><LOT_DIVISION/><OBJECT_DESCR ITEM="1"><TITLE><P>Beret zielony</P></TITLE><LOT_NO>1</LOT_NO><CPV_ADDITIONAL><CPV_CODE CODE="18443310"/></CPV_ADDITIONAL><n2016:NUTS CODE="PL"/><MAIN_SITE><P>Służba Kontrwywiadu Wojskowego, przy ul. W. Oczki 1 w Warszawie (magazyn, poziom -1).</P></MAIN_SITE><SHORT_DESCR><P>Dostawa beretu zielonego w ilości 300 szt. wykonanych zgodnie z Wojskową dokumentacją techniczno-technologiczną – WDTT nr 418/MON.</P></SHORT_DESCR><AC><AC_PRICE/></AC><NO_OPTIONS/><NO_EU_PROGR_RELATED/></OBJECT_DESCR><OBJECT_DESCR ITEM="2"><TITLE><P>Furażerka polowa sił powietrznych</P></TITLE><LOT_NO>2</LOT_NO><CPV_ADDITIONAL><CPV_CODE CODE="18440000"/></CPV_ADDITIONAL><n2016:NUTS CODE="PL"/><MAIN_SITE><P>Służba Kontrwywiadu Wojskowego, przy ul. W. Oczki 1 w Warszawie (magazyn, poziom -1).</P></MAIN_SITE><SHORT_DESCR><P>Dostawa furażerek polowych sił powietrznych w ilości 100 szt. wykonanych zgodnie z Wojskową dokumentacją techniczno-technologiczną – WDTT nr 416/MON.</P></SHORT_DESCR><AC><AC_PRICE/></AC><NO_OPTIONS/><NO_EU_PROGR_RELATED/></OBJECT_DESCR><OBJECT_DESCR ITEM="3"><TITLE><P>Czapka zimowa</P></TITLE><LOT_NO>3</LOT_NO><CPV_ADDITIONAL><CPV_CODE CODE="18443320"/></CPV_ADDITIONAL><n2016:NUTS CODE="PL"/><MAIN_SITE><P>Służba Kontrwywiadu Wojskowego, przy ul. W. Oczki 1 w Warszawie (magazyn, poziom -1).</P></MAIN_SITE><SHORT_DESCR><P>Dostawa czapek zimowych w ilości 500 szt. wykonanych zgodnie Wojskową dokumentacją techniczno-technologiczną – WDTT nr 420Z/MON.</P></SHORT_DESCR><AC><AC_PRICE/></AC><NO_OPTIONS/><NO_EU_PROGR_RELATED/></OBJECT_DESCR><OBJECT_DESCR ITEM="4"><TITLE><P>Trzewiki</P></TITLE><LOT_NO>4</LOT_NO><CPV_ADDITIONAL><CPV_CODE CODE="18832000"/></CPV_ADDITIONAL><n2016:NUTS CODE="PL"/><MAIN_SITE><P>Służba Kontrwywiadu Wojskowego, przy ul. W. Oczki 1 w Warszawie (magazyn, poziom -1).</P></MAIN_SITE><SHORT_DESCR><P>Dostawa trzewików w ilości 550 par wykonanych zgodnie z Wojskową dokumentacją techniczno-technologiczną – WDTT nr 939/MON.</P></SHORT_DESCR><AC><AC_PRICE/></AC><NO_OPTIONS/><NO_EU_PROGR_RELATED/></OBJECT_DESCR><OBJECT_DESCR ITEM="5"><TITLE><P>Trzewiki zimowe</P></TITLE><LOT_NO>5</LOT_NO><CPV_ADDITIONAL><CPV_CODE CODE="18832000"/></CPV_ADDITIONAL><n2016:NUTS CODE="PL"/><MAIN_SITE><P>Służba Kontrwywiadu Wojskowego, przy ul. W. Oczki 1 w Warszawie (magazyn, poziom -1).</P></MAIN_SITE><SHORT_DESCR><P>Dostawa trzewików zimowych w ilości 550 par wykonanych zgodnie z Wojskową dokumentacją techniczno-technologiczną – WDTT nr 933A/MON.</P></SHORT_DESCR><AC><AC_PRICE/></AC><NO_OPTIONS/><NO_EU_PROGR_RELATED/></OBJECT_DESCR><OBJECT_DESCR ITEM="6"><TITLE><P>Ubranie ochronne</P></TITLE><LOT_NO>6</LOT_NO><CPV_ADDITIONAL><CPV_CODE CODE="35811300"/></CPV_ADDITIONAL><n2016:NUTS CODE="PL"/><MAIN_SITE><P>Służba Kontrwywiadu Wojskowego, przy ul. W. Oczki 1 w Warszawie (magazyn, poziom -1).</P></MAIN_SITE><SHORT_DESCR><P>Dostawa ubrania ochronnego w ilości 500 kpl. wykonanych zgodnie z Wojskową dokumentacją techniczno-technologiczną – WDTT nr 128Z/MON.</P></SHORT_DESCR><AC><AC_PRICE/></AC><NO_OPTIONS/><NO_EU_PROGR_RELATED/></OBJECT_DESCR><OBJECT_DESCR ITEM="7"><TITLE><P>Mundur polowy</P></TITLE><LOT_NO>7</LOT_NO><CPV_ADDITIONAL><CPV_CODE CODE="35811300"/></CPV_ADDITIONAL><n2016:NUTS CODE="PL"/><MAIN_SITE><P>Służba Kontrwywiadu Wojskowego, przy ul. W. Oczki 1 w Warszawie (magazyn, poziom -1).</P></MAIN_SITE><SHORT_DESCR><P>Dostawa munduru polowego w ilości 600 kpl. wykonanych zgodnie z Wojskową dokumentacją techniczno-technologiczną – WDTT nr 124P/MON.</P></SHORT_DESCR><AC><AC_PRICE/></AC><NO_OPTIONS/><NO_EU_PROGR_RELATED/></OBJECT_DESCR><OBJECT_DESCR ITEM="8"><TITLE><P>Mundur polowy letni</P></TITLE><LOT_NO>8</LOT_NO><CPV_ADDITIONAL><CPV_CODE CODE="35811300"/></CPV_ADDITIONAL><n2016:NUTS CODE="PL"/><MAIN_SITE><P>Służba Kontrwywiadu Wojskowego, przy ul. W. Oczki 1 w Warszawie (magazyn, poziom -1).</P></MAIN_SITE><SHORT_DESCR><P>Dostawa munduru polowego letniego w ilości 600 kpl. wykonanych zgodnie z Wojskową dokumentacją techniczno-technologiczną – WDTT nr 124L/MON.</P></SHORT_DESCR><AC><AC_PRICE/></AC><NO_OPTIONS/><NO_EU_PROGR_RELATED/></OBJECT_DESCR><OBJECT_DESCR ITEM="9"><TITLE><P>Koszulobluza polowa</P></TITLE><LOT_NO>9</LOT_NO><CPV_ADDITIONAL><CPV_CODE CODE="35113470"/></CPV_ADDITIONAL><n2016:NUTS CODE="PL"/><MAIN_SITE><P>Służba Kontrwywiadu Wojskowego, przy ul. W. Oczki 1 w Warszawie (magazyn, poziom -1).</P></MAIN_SITE><SHORT_DESCR><P>Dostawa koszulobluz polowych w ilości 400 szt. wykonanych zgodnie z Wojskową dokumentacją techniczno-technologiczną – WDTT nr 304/MON.</P></SHORT_DESCR><AC><AC_PRICE/></AC><NO_OPTIONS/><NO_EU_PROGR_RELATED/></OBJECT_DESCR><OBJECT_DESCR ITEM="10"><TITLE><P>Rękawice zimowe pięciopalcowe</P></TITLE><LOT_NO>10</LOT_NO><CPV_ADDITIONAL><CPV_CODE CODE="18424000"/></CPV_ADDITIONAL><n2016:NUTS CODE="PL"/><MAIN_SITE><P>Służba Kontrwywiadu Wojskowego, przy ul. W. Oczki 1 w Warszawie (magazyn, poziom -1).</P></MAIN_SITE><SHORT_DESCR><P>Dostawa rękawic zimowych pięciopalcowych w ilości 400 par wykonanych zgodnie z Wojskową dokumentacją techniczno-technologiczną – WDTT nr 615A/MON.</P></SHORT_DESCR><AC><AC_PRICE/></AC><NO_OPTIONS/><NO_EU_PROGR_RELATED/></OBJECT_DESCR><OBJECT_DESCR ITEM="11"><TITLE><P>Karimata</P></TITLE><LOT_NO>11</LOT_NO><CPV_ADDITIONAL><CPV_CODE CODE="37414100"/></CPV_ADDITIONAL><n2016:NUTS CODE="PL"/><MAIN_SITE><P>Służba Kontrwywiadu Wojskowego, przy ul. W. Oczki 1 w Warszawie (magazyn, poziom -1).</P></MAIN_SITE><SHORT_DESCR><P>Dostawa karimaty w ilości 200 szt. wykonanych zgodnie z Wojskową dokumentacją techniczno-technologiczną – WDTT nr 730/MON.</P></SHORT_DESCR><AC><AC_PRICE/></AC><NO_OPTIONS/><NO_EU_PROGR_RELATED/></OBJECT_DESCR><OBJECT_DESCR ITEM="12"><TITLE><P>Szelki do przenoszenia oporządzenia</P></TITLE><LOT_NO>12</LOT_NO><CPV_ADDITIONAL><CPV_CODE CODE="18323000"/></CPV_ADDITIONAL><n2016:NUTS CODE="PL"/><MAIN_SITE><P>Służba Kontrwywiadu Wojskowego, przy ul. W. Oczki 1 w Warszawie (magazyn, poziom -1).</P></MAIN_SITE><SHORT_DESCR><P>Dostawa szelek do przenoszenia oporządzenia w ilości 200 szt. wykonanych zgodnie z Wojskową dokumentacją techniczno-technologiczną – WDTT nr 988/MON.</P></SHORT_DESCR><AC><AC_PRICE/></AC><NO_OPTIONS/><NO_EU_PROGR_RELATED/></OBJECT_DESCR><OBJECT_DESCR ITEM="13"><TITLE><P>Pas żołnierski</P></TITLE><LOT_NO>13</LOT_NO><CPV_ADDITIONAL><CPV_CODE CODE="18425000"/></CPV_ADDITIONAL><n2016:NUTS CODE="PL"/><MAIN_SITE><P>Służba Kontrwywiadu Wojskowego, przy ul. W. Oczki 1 w Warszawie (magazyn, poziom -1).</P></MAIN_SITE><SHORT_DESCR><P>Dostawa pasów żołnierskich w ilości 200 szt. wykonanych zgodnie z Wojskową dokumentacją techniczno-technologiczną – WDTT nr 957/MON.</P></SHORT_DESCR><AC><AC_PRICE/></AC><NO_OPTIONS/><NO_EU_PROGR_RELATED/></OBJECT_DESCR><OBJECT_DESCR ITEM="14"><TITLE><P>Skarpety zimowe</P></TITLE><LOT_NO>14</LOT_NO><CPV_ADDITIONAL><CPV_CODE CODE="18317000"/></CPV_ADDITIONAL><n2016:NUTS CODE="PL"/><MAIN_SITE><P>Służba Kontrwywiadu Wojskowego, przy ul. W. Oczki 1 w Warszawie (magazyn, poziom -1).</P></MAIN_SITE><SHORT_DESCR><P>Dostawa skarpet zimowych w ilości 1 500 par wykonanych zgodnie z Wojskową dokumentacją techniczno-technologiczną – WDTT nr 539/MON.</P></SHORT_DESCR><AC><AC_PRICE/></AC><NO_OPTIONS/><NO_EU_PROGR_RELATED/></OBJECT_DESCR><OBJECT_DESCR ITEM="15"><TITLE><P>Skarpety letnie</P></TITLE><LOT_NO>15</LOT_NO><CPV_ADDITIONAL><CPV_CODE CODE="18317000"/></CPV_ADDITIONAL><n2016:NUTS CODE="PL"/><MAIN_SITE><P>Służba Kontrwywiadu Wojskowego, przy ul. W. Oczki 1 w Warszawie (magazyn, poziom -1).</P></MAIN_SITE><SHORT_DESCR><P>Dostawa skarpet letnich w ilości 1 000 par wykonanych zgodnie z Wojskową dokumentacją techniczno-technologiczną – WDTT nr 538/MON.</P></SHORT_DESCR><AC><AC_PRICE/></AC><NO_OPTIONS/><NO_EU_PROGR_RELATED/></OBJECT_DESCR><OBJECT_DESCR ITEM="16"><TITLE><P>Bielizna zimowa</P></TITLE><LOT_NO>16</LOT_NO><CPV_ADDITIONAL><CPV_CODE CODE="18310000"/></CPV_ADDITIONAL><n2016:NUTS CODE="PL"/><MAIN_SITE><P>Służba Kontrwywiadu Wojskowego, przy ul. W. Oczki 1 w Warszawie (magazyn, poziom -1).</P></MAIN_SITE><SHORT_DESCR><P>Dostawa bielizny zimowej w ilości 1000 kpl. wykonanych zgodnie z Wojskową dokumentacją techniczno-technologiczną – WDTT nr 507T/MON.</P></SHORT_DESCR><AC><AC_PRICE/></AC><NO_OPTIONS/><NO_EU_PROGR_RELATED/></OBJECT_DESCR><OBJECT_DESCR ITEM="17"><TITLE><P>Bielizna letnia</P></TITLE><LOT_NO>17</LOT_NO><CPV_ADDITIONAL><CPV_CODE CODE="18310000"/></CPV_ADDITIONAL><n2016:NUTS CODE="PL"/><MAIN_SITE><P>Służba Kontrwywiadu Wojskowego, przy ul. W. Oczki 1 w Warszawie (magazyn, poziom -1).</P></MAIN_SITE><SHORT_DESCR><P>Dostawa bielizny letniej w ilości 1000 kpl. wykonanych zgodnie z Wojskową dokumentacją techniczno-technologiczną – WDTT nr 518L/MON.</P></SHORT_DESCR><AC><AC_PRICE/></AC><NO_OPTIONS/><NO_EU_PROGR_RELATED/></OBJECT_DESCR><OBJECT_DESCR ITEM="18"><TITLE><P>Bluza ocieplająca</P></TITLE><LOT_NO>18</LOT_NO><CPV_ADDITIONAL><CPV_CODE CODE="18310000"/></CPV_ADDITIONAL><n2016:NUTS CODE="PL"/><MAIN_SITE><P>Służba Kontrwywiadu Wojskowego, przy ul. W. Oczki 1 w Warszawie (magazyn, poziom -1).</P></MAIN_SITE><SHORT_DESCR><P>Dostawa bluz ocieplających w ilości 250 szt. wykonanych zgodnie z Wojskową dokumentacją techniczno-technologiczną – WDTT nr 546/MON.</P></SHORT_DESCR><AC><AC_PRICE/></AC><NO_OPTIONS/><NO_EU_PROGR_RELATED/></OBJECT_DESCR></OBJECT_CONTRACT><PROCEDURE><PT_OPEN/><NO_CONTRACT_COVERED_GPA/><NOTICE_NUMBER_OJ>2020/S 125-305874</NOTICE_NUMBER_OJ></PROCEDURE><AWARD_CONTRACT ITEM="1"><LOT_NO>1</LOT_NO><TITLE><P>Beret zielony</P></TITLE><AWARDED_CONTRACT><DATE_CONCLUSION_CONTRACT>2020-09-15</DATE_CONCLUSION_CONTRACT><TENDERS><NB_TENDERS_RECEIVED>1</NB_TENDERS_RECEIVED><NB_TENDERS_RECEIVED_SME>1</NB_TENDERS_RECEIVED_SME><NB_TENDERS_RECEIVED_EMEANS>1</NB_TENDERS_RECEIVED_EMEANS></TENDERS><CONTRACTORS><NO_AWARDED_TO_GROUP/><CONTRACTOR><ADDRESS_CONTRACTOR><OFFICIALNAME>„Hako” Sp. z o.o.</OFFICIALNAME><ADDRESS>ul. Borzymowska 30</ADDRESS><TOWN>Warszawa</TOWN><POSTAL_CODE>03-565</POSTAL_CODE><COUNTRY VALUE="PL"/><n2016:NUTS CODE="PL"/></ADDRESS_CONTRACTOR><SME/></CONTRACTOR></CONTRACTORS><VALUES><VAL_ESTIMATED_TOTAL CURRENCY="PLN">9756.10</VAL_ESTIMATED_TOTAL><VAL_TOTAL CURRENCY="PLN">15000.00</VAL_TOTAL></VALUES></AWARDED_CONTRACT></AWARD_CONTRACT><AWARD_CONTRACT ITEM="2"><LOT_NO>2</LOT_NO><TITLE><P>Furażerka polowa sił powietrznych</P></TITLE><AWARDED_CONTRACT><DATE_CONCLUSION_CONTRACT>2020-09-15</DATE_CONCLUSION_CONTRACT><TENDERS><NB_TENDERS_RECEIVED>1</NB_TENDERS_RECEIVED><NB_TENDERS_RECEIVED_SME>1</NB_TENDERS_RECEIVED_SME><NB_TENDERS_RECEIVED_EMEANS>1</NB_TENDERS_RECEIVED_EMEANS></TENDERS><CONTRACTORS><NO_AWARDED_TO_GROUP/><CONTRACTOR><ADDRESS_CONTRACTOR><OFFICIALNAME>„Hako” Sp. z o.o.</OFFICIALNAME><ADDRESS>ul. Borzymowska 30</ADDRESS><TOWN>Warszawa</TOWN><POSTAL_CODE>03-565</POSTAL_CODE><COUNTRY VALUE="PL"/><n2016:NUTS CODE="PL"/></ADDRESS_CONTRACTOR><SME/></CONTRACTOR></CONTRACTORS><VALUES><VAL_ESTIMATED_TOTAL CURRENCY="PLN">3658.54</VAL_ESTIMATED_TOTAL><VAL_TOTAL CURRENCY="PLN">7500.00</VAL_TOTAL></VALUES></AWARDED_CONTRACT></AWARD_CONTRACT><AWARD_CONTRACT ITEM="3"><LOT_NO>3</LOT_NO><TITLE><P>Czapka zimowa</P></TITLE><AWARDED_CONTRACT><DATE_CONCLUSION_CONTRACT>2020-09-28</DATE_CONCLUSION_CONTRACT><TENDERS><NB_TENDERS_RECEIVED>1</NB_TENDERS_RECEIVED><NB_TENDERS_RECEIVED_SME>1</NB_TENDERS_RECEIVED_SME><NB_TENDERS_RECEIVED_EMEANS>1</NB_TENDERS_RECEIVED_EMEANS></TENDERS><CONTRACTORS><NO_AWARDED_TO_GROUP/><CONTRACTOR><ADDRESS_CONTRACTOR><OFFICIALNAME>San Marko Sp. z o.o.</OFFICIALNAME><ADDRESS>ul. Samuela Lindego 4</ADDRESS><TOWN>Poznań</TOWN><POSTAL_CODE>60-573</POSTAL_CODE><COUNTRY VALUE="PL"/><n2016:NUTS CODE="PL"/></ADDRESS_CONTRACTOR><SME/></CONTRACTOR></CONTRACTORS><VALUES><VAL_ESTIMATED_TOTAL CURRENCY="PLN">19918.70</VAL_ESTIMATED_TOTAL><VAL_TOTAL CURRENCY="PLN">27500.00</VAL_TOTAL></VALUES></AWARDED_CONTRACT></AWARD_CONTRACT><AWARD_CONTRACT ITEM="4"><LOT_NO>4</LOT_NO><TITLE><P>Trzewiki</P></TITLE><AWARDED_CONTRACT><DATE_CONCLUSION_CONTRACT>2020-09-29</DATE_CONCLUSION_CONTRACT><TENDERS><NB_TENDERS_RECEIVED>2</NB_TENDERS_RECEIVED><NB_TENDERS_RECEIVED_SME>2</NB_TENDERS_RECEIVED_SME><NB_TENDERS_RECEIVED_EMEANS>2</NB_TENDERS_RECEIVED_EMEANS></TENDERS><CONTRACTORS><NO_AWARDED_TO_GROUP/><CONTRACTOR><ADDRESS_CONTRACTOR><OFFICIALNAME>Gregor S.A. (lider konsorcjum), Przedsiębiorstwo Produkcyjno-Usługowo-Handlowe Arm-Ex Barbara Mruk, Mariusz Mruk Sp. J. (partner konsorcjum)</OFFICIALNAME><ADDRESS>ul. Tczewska 1A</ADDRESS><TOWN>Pszczółki</TOWN><POSTAL_CODE>83-032</POSTAL_CODE><COUNTRY VALUE="PL"/><n2016:NUTS CODE="PL"/></ADDRESS_CONTRACTOR><SME/></CONTRACTOR></CONTRACTORS><VALUES><VAL_ESTIMATED_TOTAL CURRENCY="PLN">232520.32</VAL_ESTIMATED_TOTAL><VAL_TOTAL CURRENCY="PLN">219450.00</VAL_TOTAL></VALUES></AWARDED_CONTRACT></AWARD_CONTRACT><AWARD_CONTRACT ITEM="5"><LOT_NO>5</LOT_NO><TITLE><P>Trzewiki zimowe</P></TITLE><AWARDED_CONTRACT><DATE_CONCLUSION_CONTRACT>2020-09-28</DATE_CONCLUSION_CONTRACT><TENDERS><NB_TENDERS_RECEIVED>2</NB_TENDERS_RECEIVED><NB_TENDERS_RECEIVED_SME>2</NB_TENDERS_RECEIVED_SME><NB_TENDERS_RECEIVED_EMEANS>2</NB_TENDERS_RECEIVED_EMEANS></TENDERS><CONTRACTORS><NO_AWARDED_TO_GROUP/><CONTRACTOR><ADDRESS_CONTRACTOR><OFFICIALNAME>Gregor S.A. (lider konsorcjum), Przedsiębiorstwo Produkcyjno-Usługowo-Handlowe Arm-Ex Barbara Mruk, Mariusz Mruk Sp. J. (partner konsorcjum)</OFFICIALNAME><ADDRESS>ul. Tczewska 1A</ADDRESS><TOWN>Pszczółki</TOWN><POSTAL_CODE>83-032</POSTAL_CODE><COUNTRY VALUE="PL"/><n2016:NUTS CODE="PL"/></ADDRESS_CONTRACTOR><SME/></CONTRACTOR></CONTRACTORS><VALUES><VAL_ESTIMATED_TOTAL CURRENCY="PLN">223577.22</VAL_ESTIMATED_TOTAL><VAL_TOTAL CURRENCY="PLN">174900.00</VAL_TOTAL></VALUES></AWARDED_CONTRACT></AWARD_CONTRACT><AWARD_CONTRACT ITEM="6"><LOT_NO>6</LOT_NO><TITLE><P>Ubranie ochronne</P></TITLE><NO_AWARDED_CONTRACT><PROCUREMENT_UNSUCCESSFUL/></NO_AWARDED_CONTRACT></AWARD_CONTRACT><AWARD_CONTRACT ITEM="7"><LOT_NO>7</LOT_NO><TITLE><P>Mundur polowy</P></TITLE><AWARDED_CONTRACT><DATE_CONCLUSION_CONTRACT>2020-09-28</DATE_CONCLUSION_CONTRACT><TENDERS><NB_TENDERS_RECEIVED>2</NB_TENDERS_RECEIVED><NB_TENDERS_RECEIVED_SME>2</NB_TENDERS_RECEIVED_SME><NB_TENDERS_RECEIVED_EMEANS>2</NB_TENDERS_RECEIVED_EMEANS></TENDERS><CONTRACTORS><NO_AWARDED_TO_GROUP/><CONTRACTOR><ADDRESS_CONTRACTOR><OFFICIALNAME>Spółdzielnia Inwalidów Elremet</OFFICIALNAME><ADDRESS>ul. Prosta 35</ADDRESS><TOWN>Biała Podlaska</TOWN><POSTAL_CODE>21-500</POSTAL_CODE><COUNTRY VALUE="PL"/><n2016:NUTS CODE="PL"/></ADDRESS_CONTRACTOR><SME/></CONTRACTOR></CONTRACTORS><VALUES><VAL_ESTIMATED_TOTAL CURRENCY="PLN">219512.20</VAL_ESTIMATED_TOTAL><VAL_TOTAL CURRENCY="PLN">208800.00</VAL_TOTAL></VALUES></AWARDED_CONTRACT></AWARD_CONTRACT><AWARD_CONTRACT ITEM="8"><LOT_NO>8</LOT_NO><TITLE><P>Mundur polowy letni</P></TITLE><AWARDED_CONTRACT><DATE_CONCLUSION_CONTRACT>2020-09-28</DATE_CONCLUSION_CONTRACT><TENDERS><NB_TENDERS_RECEIVED>3</NB_TENDERS_RECEIVED><NB_TENDERS_RECEIVED_SME>3</NB_TENDERS_RECEIVED_SME><NB_TENDERS_RECEIVED_EMEANS>3</NB_TENDERS_RECEIVED_EMEANS></TENDERS><CONTRACTORS><NO_AWARDED_TO_GROUP/><CONTRACTOR><ADDRESS_CONTRACTOR><OFFICIALNAME>Spółdzielnia Inwalidów Elremet</OFFICIALNAME><ADDRESS>ul. Prosta 35</ADDRESS><TOWN>Biała Podlaska</TOWN><POSTAL_CODE>21-500</POSTAL_CODE><COUNTRY VALUE="PL"/><n2016:NUTS CODE="PL"/></ADDRESS_CONTRACTOR><SME/></CONTRACTOR></CONTRACTORS><VALUES><VAL_ESTIMATED_TOTAL CURRENCY="PLN">219512.20</VAL_ESTIMATED_TOTAL><VAL_TOTAL CURRENCY="PLN">208800.00</VAL_TOTAL></VALUES></AWARDED_CONTRACT></AWARD_CONTRACT><AWARD_CONTRACT ITEM="9"><LOT_NO>9</LOT_NO><TITLE><P>Koszulobluza polowa</P></TITLE><AWARDED_CONTRACT><DATE_CONCLUSION_CONTRACT>2020-09-28</DATE_CONCLUSION_CONTRACT><TENDERS><NB_TENDERS_RECEIVED>1</NB_TENDERS_RECEIVED><NB_TENDERS_RECEIVED_SME>1</NB_TENDERS_RECEIVED_SME><NB_TENDERS_RECEIVED_EMEANS>1</NB_TENDERS_RECEIVED_EMEANS></TENDERS><CONTRACTORS><NO_AWARDED_TO_GROUP/><CONTRACTOR><ADDRESS_CONTRACTOR><OFFICIALNAME>Spółdzielnia Inwalidów Elremet</OFFICIALNAME><ADDRESS>ul. Prosta 35</ADDRESS><TOWN>Biała Podlaska</TOWN><POSTAL_CODE>21-500</POSTAL_CODE><COUNTRY VALUE="PL"/><n2016:NUTS CODE="PL"/></ADDRESS_CONTRACTOR><SME/></CONTRACTOR></CONTRACTORS><VALUES><VAL_ESTIMATED_TOTAL CURRENCY="PLN">42276.42</VAL_ESTIMATED_TOTAL><VAL_TOTAL CURRENCY="PLN">39600.00</VAL_TOTAL></VALUES></AWARDED_CONTRACT></AWARD_CONTRACT><AWARD_CONTRACT ITEM="10"><LOT_NO>10</LOT_NO><TITLE><P>Rękawice zimowe pięciopalcowe</P></TITLE><AWARDED_CONTRACT><DATE_CONCLUSION_CONTRACT>2020-10-01</DATE_CONCLUSION_CONTRACT><TENDERS><NB_TENDERS_RECEIVED>1</NB_TENDERS_RECEIVED><NB_TENDERS_RECEIVED_SME>1</NB_TENDERS_RECEIVED_SME><NB_TENDERS_RECEIVED_EMEANS>1</NB_TENDERS_RECEIVED_EMEANS></TENDERS><CONTRACTORS><NO_AWARDED_TO_GROUP/><CONTRACTOR><ADDRESS_CONTRACTOR><OFFICIALNAME>Bogmar BB Sp. z o.o., Sp. k.</OFFICIALNAME><ADDRESS>ul. Jana Sobieskiego 160</ADDRESS><TOWN>Bielsko-Biała</TOWN><POSTAL_CODE>43-300</POSTAL_CODE><COUNTRY VALUE="PL"/><n2016:NUTS CODE="PL"/></ADDRESS_CONTRACTOR><SME/></CONTRACTOR></CONTRACTORS><VALUES><VAL_ESTIMATED_TOTAL CURRENCY="PLN">16260.16</VAL_ESTIMATED_TOTAL><VAL_TOTAL CURRENCY="PLN">18400.00</VAL_TOTAL></VALUES></AWARDED_CONTRACT></AWARD_CONTRACT><AWARD_CONTRACT ITEM="11"><LOT_NO>11</LOT_NO><TITLE><P>Karimata</P></TITLE><AWARDED_CONTRACT><DATE_CONCLUSION_CONTRACT>2020-09-28</DATE_CONCLUSION_CONTRACT><TENDERS><NB_TENDERS_RECEIVED>1</NB_TENDERS_RECEIVED><NB_TENDERS_RECEIVED_SME>1</NB_TENDERS_RECEIVED_SME><NB_TENDERS_RECEIVED_EMEANS>1</NB_TENDERS_RECEIVED_EMEANS></TENDERS><CONTRACTORS><NO_AWARDED_TO_GROUP/><CONTRACTOR><ADDRESS_CONTRACTOR><OFFICIALNAME>„Callida” Sp. z o.o.</OFFICIALNAME><ADDRESS>ul. Lenartowicza 6/8</ADDRESS><TOWN>Częstochowa</TOWN><POSTAL_CODE>42-207</POSTAL_CODE><COUNTRY VALUE="PL"/><n2016:NUTS CODE="PL"/></ADDRESS_CONTRACTOR><SME/></CONTRACTOR></CONTRACTORS><VALUES><VAL_ESTIMATED_TOTAL CURRENCY="PLN">6829.27</VAL_ESTIMATED_TOTAL><VAL_TOTAL CURRENCY="PLN">8580.49</VAL_TOTAL></VALUES></AWARDED_CONTRACT></AWARD_CONTRACT><AWARD_CONTRACT ITEM="12"><LOT_NO>12</LOT_NO><TITLE><P>Szelki do przenoszenia oporządzenia</P></TITLE><AWARDED_CONTRACT><DATE_CONCLUSION_CONTRACT>2020-10-01</DATE_CONCLUSION_CONTRACT><TENDERS><NB_TENDERS_RECEIVED>1</NB_TENDERS_RECEIVED><NB_TENDERS_RECEIVED_SME>1</NB_TENDERS_RECEIVED_SME><NB_TENDERS_RECEIVED_EMEANS>1</NB_TENDERS_RECEIVED_EMEANS></TENDERS><CONTRACTORS><NO_AWARDED_TO_GROUP/><CONTRACTOR><ADDRESS_CONTRACTOR><OFFICIALNAME>Przedsiębiorstwo Produkcyjno-Handlowe „Polskór” Bogdan Stasiołek</OFFICIALNAME><ADDRESS>ul. Szczęśliwa 31</ADDRESS><TOWN>Tomaszów Mazowiecki</TOWN><POSTAL_CODE>97-200</POSTAL_CODE><COUNTRY VALUE="PL"/><n2016:NUTS CODE="PL"/></ADDRESS_CONTRACTOR><SME/></CONTRACTOR></CONTRACTORS><VALUES><VAL_ESTIMATED_TOTAL CURRENCY="PLN">24390.24</VAL_ESTIMATED_TOTAL><VAL_TOTAL CURRENCY="PLN">44000.00</VAL_TOTAL></VALUES></AWARDED_CONTRACT></AWARD_CONTRACT><AWARD_CONTRACT ITEM="13"><LOT_NO>13</LOT_NO><TITLE><P>Pas żołnierski</P></TITLE><AWARDED_CONTRACT><DATE_CONCLUSION_CONTRACT>2020-09-28</DATE_CONCLUSION_CONTRACT><TENDERS><NB_TENDERS_RECEIVED>3</NB_TENDERS_RECEIVED><NB_TENDERS_RECEIVED_SME>3</NB_TENDERS_RECEIVED_SME><NB_TENDERS_RECEIVED_EMEANS>3</NB_TENDERS_RECEIVED_EMEANS></TENDERS><CONTRACTORS><NO_AWARDED_TO_GROUP/><CONTRACTOR><ADDRESS_CONTRACTOR><OFFICIALNAME>„Cobby” Sp. z o.o., Sp. k.</OFFICIALNAME><ADDRESS>ul. Podolańska 44B</ADDRESS><TOWN>Poznań</TOWN><POSTAL_CODE>60-626</POSTAL_CODE><COUNTRY VALUE="PL"/><n2016:NUTS CODE="PL"/></ADDRESS_CONTRACTOR><SME/></CONTRACTOR></CONTRACTORS><VALUES><VAL_ESTIMATED_TOTAL CURRENCY="PLN">6504.07</VAL_ESTIMATED_TOTAL><VAL_TOTAL CURRENCY="PLN">4600.00</VAL_TOTAL></VALUES></AWARDED_CONTRACT></AWARD_CONTRACT><AWARD_CONTRACT ITEM="14"><LOT_NO>14</LOT_NO><TITLE><P>Skarpety zimowe</P></TITLE><AWARDED_CONTRACT><DATE_CONCLUSION_CONTRACT>2020-09-28</DATE_CONCLUSION_CONTRACT><TENDERS><NB_TENDERS_RECEIVED>1</NB_TENDERS_RECEIVED><NB_TENDERS_RECEIVED_SME>1</NB_TENDERS_RECEIVED_SME><NB_TENDERS_RECEIVED_EMEANS>1</NB_TENDERS_RECEIVED_EMEANS></TENDERS><CONTRACTORS><NO_AWARDED_TO_GROUP/><CONTRACTOR><ADDRESS_CONTRACTOR><OFFICIALNAME>Marek Krajewski Przedsiębiorstwo Produkcyjno-Handlowo-Usługowe „Krajewski” w spadku</OFFICIALNAME><ADDRESS>ul. Nadbzurzańska 19</ADDRESS><TOWN>Łowicz</TOWN><POSTAL_CODE>99-400</POSTAL_CODE><COUNTRY VALUE="PL"/><n2016:NUTS CODE="PL"/></ADDRESS_CONTRACTOR><SME/></CONTRACTOR></CONTRACTORS><VALUES><VAL_ESTIMATED_TOTAL CURRENCY="PLN">14634.15</VAL_ESTIMATED_TOTAL><VAL_TOTAL CURRENCY="PLN">19280.49</VAL_TOTAL></VALUES></AWARDED_CONTRACT></AWARD_CONTRACT><AWARD_CONTRACT ITEM="15"><LOT_NO>15</LOT_NO><TITLE><P>Skarpety letnie</P></TITLE><AWARDED_CONTRACT><DATE_CONCLUSION_CONTRACT>2020-09-28</DATE_CONCLUSION_CONTRACT><TENDERS><NB_TENDERS_RECEIVED>1</NB_TENDERS_RECEIVED><NB_TENDERS_RECEIVED_SME>1</NB_TENDERS_RECEIVED_SME><NB_TENDERS_RECEIVED_EMEANS>1</NB_TENDERS_RECEIVED_EMEANS></TENDERS><CONTRACTORS><NO_AWARDED_TO_GROUP/><CONTRACTOR><ADDRESS_CONTRACTOR><OFFICIALNAME>Marek Krajewski Przedsiębiorstwo Produkcyjno-Handlowo-Usługowe „Krajewski” w spadku</OFFICIALNAME><ADDRESS>ul. Nadbzurzańska 19</ADDRESS><TOWN>Łowicz</TOWN><POSTAL_CODE>99-400</POSTAL_CODE><COUNTRY VALUE="PL"/><n2016:NUTS CODE="PL"/></ADDRESS_CONTRACTOR><SME/></CONTRACTOR></CONTRACTORS><VALUES><VAL_ESTIMATED_TOTAL CURRENCY="PLN">5284.55</VAL_ESTIMATED_TOTAL><VAL_TOTAL CURRENCY="PLN">7601.63</VAL_TOTAL></VALUES></AWARDED_CONTRACT></AWARD_CONTRACT><AWARD_CONTRACT ITEM="16"><LOT_NO>16</LOT_NO><TITLE><P>Bielizna zimowa</P></TITLE><AWARDED_CONTRACT><DATE_CONCLUSION_CONTRACT>2020-09-28</DATE_CONCLUSION_CONTRACT><TENDERS><NB_TENDERS_RECEIVED>1</NB_TENDERS_RECEIVED><NB_TENDERS_RECEIVED_SME>1</NB_TENDERS_RECEIVED_SME><NB_TENDERS_RECEIVED_EMEANS>1</NB_TENDERS_RECEIVED_EMEANS></TENDERS><CONTRACTORS><NO_AWARDED_TO_GROUP/><CONTRACTOR><ADDRESS_CONTRACTOR><OFFICIALNAME>Trawena Sp. z o.o., Sp. k.</OFFICIALNAME><TOWN>Trawniki 624 C</TOWN><POSTAL_CODE>21-044</POSTAL_CODE><COUNTRY VALUE="PL"/><n2016:NUTS CODE="PL"/></ADDRESS_CONTRACTOR><SME/></CONTRACTOR></CONTRACTORS><VALUES><VAL_ESTIMATED_TOTAL CURRENCY="PLN">121951.22</VAL_ESTIMATED_TOTAL><VAL_TOTAL CURRENCY="PLN">121138.21</VAL_TOTAL></VALUES></AWARDED_CONTRACT></AWARD_CONTRACT><AWARD_CONTRACT ITEM="17"><LOT_NO>17</LOT_NO><TITLE><P>Bielizna letnia</P></TITLE><AWARDED_CONTRACT><DATE_CONCLUSION_CONTRACT>2020-10-01</DATE_CONCLUSION_CONTRACT><TENDERS><NB_TENDERS_RECEIVED>1</NB_TENDERS_RECEIVED><NB_TENDERS_RECEIVED_SME>1</NB_TENDERS_RECEIVED_SME><NB_TENDERS_RECEIVED_EMEANS>1</NB_TENDERS_RECEIVED_EMEANS></TENDERS><CONTRACTORS><NO_AWARDED_TO_GROUP/><CONTRACTOR><ADDRESS_CONTRACTOR><OFFICIALNAME>Bogmar BB Sp. z o.o., Sp. k.</OFFICIALNAME><ADDRESS>ul. Jana Sobieskiego 160</ADDRESS><TOWN>Bielsko-Biała</TOWN><POSTAL_CODE>43-300</POSTAL_CODE><COUNTRY VALUE="PL"/><n2016:NUTS CODE="PL"/></ADDRESS_CONTRACTOR><SME/></CONTRACTOR></CONTRACTORS><VALUES><VAL_ESTIMATED_TOTAL CURRENCY="PLN">36585.37</VAL_ESTIMATED_TOTAL><VAL_TOTAL CURRENCY="PLN">28000.00</VAL_TOTAL></VALUES></AWARDED_CONTRACT></AWARD_CONTRACT><AWARD_CONTRACT ITEM="18"><LOT_NO>18</LOT_NO><TITLE><P>Bluza ocieplająca</P></TITLE><AWARDED_CONTRACT><DATE_CONCLUSION_CONTRACT>2020-09-28</DATE_CONCLUSION_CONTRACT><TENDERS><NB_TENDERS_RECEIVED>1</NB_TENDERS_RECEIVED><NB_TENDERS_RECEIVED_SME>1</NB_TENDERS_RECEIVED_SME><NB_TENDERS_RECEIVED_EMEANS>1</NB_TENDERS_RECEIVED_EMEANS></TENDERS><CONTRACTORS><NO_AWARDED_TO_GROUP/><CONTRACTOR><ADDRESS_CONTRACTOR><OFFICIALNAME>Trawena Sp. z o.o., Sp. k.</OFFICIALNAME><TOWN>Trawniki 624 C</TOWN><POSTAL_CODE>21-044</POSTAL_CODE><COUNTRY VALUE="PL"/><n2016:NUTS CODE="PL"/></ADDRESS_CONTRACTOR><SME/></CONTRACTOR></CONTRACTORS><VALUES><VAL_ESTIMATED_TOTAL CURRENCY="PLN">20325.20</VAL_ESTIMATED_TOTAL><VAL_TOTAL CURRENCY="PLN">62500.00</VAL_TOTAL></VALUES></AWARDED_CONTRACT></AWARD_CONTRACT><COMPLEMENTARY_INFO><ADDRESS_REVIEW_BODY><OFFICIALNAME>Prezes Krajowej Izby Odwoławczej</OFFICIALNAME><ADDRESS>ul. Postępu 17a</ADDRESS><TOWN>Warszawa</TOWN><POSTAL_CODE>02-676</POSTAL_CODE><COUNTRY VALUE="PL"/><PHONE>+42 224587840</PHONE><E_MAIL>odwolania@uzp.gov.pl</E_MAIL><FAX>+48 224587800</FAX><URL>http://www.uzp.gov.pl</URL></ADDRESS_REVIEW_BODY><ADDRESS_MEDIATION_BODY><OFFICIALNAME>Krajowa Izba Odwoławcza</OFFICIALNAME><ADDRESS>ul. Postępu 17a</ADDRESS><TOWN>Warszawa</TOWN><POSTAL_CODE>02-676</POSTAL_CODE><COUNTRY VALUE="PL"/><PHONE>+42 224587840</PHONE><E_MAIL>odwolania@uzp.gov.pl</E_MAIL><FAX>+48 224587800</FAX><URL>http://www.uzp.gov.pl</URL></ADDRESS_MEDIATION_BODY><REVIEW_PROCEDURE><P>Odwołanie wnosi się w terminie 10 dni od dnia przesłania informacji o czynności Zamawiającego stanowiącej podstawę jego wniesienia – jeżeli zostały przesłane w sposób określony w art. 180 ust. 5 zdanie drugie ustawy. Odwołanie wobec treści ogłoszenia o zamówieniu a także postanowień Specyfikacji Istotnych Warunków Zamówienia (SIWZ) wnosi się w terminie 10 dni od publikacji ogłoszenia w Dzienniku Urzędowym Unii Europejskiej lub zamieszczenia SIWZ na stronie internetowej. Odwołanie wobec innych czynności Zamawiającego niż określone wcześniej wnosi się w terminie 10 dni od dnia, w którym powzięto lub przy zachowaniu należytej staranności można było powziąć wiadomość o okolicznościach stanowiących podstawę jego wniesienia.</P></REVIEW_PROCEDURE><ADDRESS_REVIEW_INFO><OFFICIALNAME>Krajowa Izba Odwoławcza – Sekretariat Departamentu Odwołań</OFFICIALNAME><ADDRESS>ul. Postępu 17a</ADDRESS><TOWN>Warszawa</TOWN><POSTAL_CODE>02-676</POSTAL_CODE><COUNTRY VALUE="PL"/><PHONE>+48 224587801</PHONE><E_MAIL>odwolania@uzp.gov.pl</E_MAIL><FAX>+48 224587800/+48 224587803</FAX><URL>http://www.uzp.gov.pl</URL></ADDRESS_REVIEW_INFO><DATE_DISPATCH_NOTICE>2020-10-07</DATE_DISPATCH_NOTICE></COMPLEMENTARY_INFO></F03_2014></FORM_SECTION></TED_EXPORT>